dynamic_registry/__init__.py
dynamic_registry/_entry.py
dynamic_registry/_registry.py
dynamic_registry-1.0.1.dist-info/LICENSE
dynamic_registry-1.0.1.dist-info/METADATA
dynamic_registry-1.0.1.dist-info/WHEEL
dynamic_registry-1.0.1.dist-info/RECORD
