Metadata-Version: 2.3
Name: dynamic_registry
Version: 1.0.1
Summary: Registry with dynamic entries (can be enriched with data in runtime)
License: MIT
Author: endusol
Author-email: pdima.endusol@gmail.com
Requires-Python: >=3.9
Classifier: License :: OSI Approved :: MIT License
Classifier: Programming Language :: Python :: 3
Classifier: Programming Language :: Python :: 3.9
Classifier: Programming Language :: Python :: 3.10
Classifier: Programming Language :: Python :: 3.11
Classifier: Programming Language :: Python :: 3.12
Classifier: Programming Language :: Python :: 3.13
Project-URL: Homepage, https://github.com/endusol/dynamic-registry
Project-URL: Issues, https://github.com/endusol/dynamic-registry/issues
